flaskonf/__init__.py
flaskonf/_nbdev.py
flaskonf/api.py
flaskonf/static/css/bootstrap.css
flaskonf/static/js/bootstrap.min.js
flaskonf/static/js/bootstrap.min.js.map
flaskonf/static/js/jquery.min.js
flaskonf/templates/get_page.html
flaskonf-0.0.4.dist-info/LICENSE
flaskonf-0.0.4.dist-info/METADATA
flaskonf-0.0.4.dist-info/WHEEL
flaskonf-0.0.4.dist-info/entry_points.txt
flaskonf-0.0.4.dist-info/top_level.txt
flaskonf-0.0.4.dist-info/RECORD
